swagger_spec_validator3
