Metadata-Version: 1.1
Name: swagger-spec-validator3
Version: 3.0.4
Summary: Validation of Swagger specifications
Home-page: http://github.com/Yelp/swagger_spec_validator
Author: John Billings
Author-email: billings@yelp.com
License: Apache License, Version 2.0
Platform: UNKNOWN
Classifier: Development Status :: 5 - Production/Stable
Classifier: Intended Audience :: Developers
Classifier: Topic :: Software Development :: Libraries :: Python Modules
Classifier: Operating System :: OS Independent
Classifier: Programming Language :: Python :: 2.7
Classifier: Programming Language :: Python :: 3.4
Classifier: Programming Language :: Python :: 3.5
Classifier: Programming Language :: Python :: 3.6
